setup.py
kernunos/__init__.py
kernunos/__main__.py
kernunos/core.py
kernunos.egg-info/PKG-INFO
kernunos.egg-info/SOURCES.txt
kernunos.egg-info/dependency_links.txt
kernunos.egg-info/requires.txt
kernunos.egg-info/top_level.txt