Metadata-Version: 1.0
Name: kernunos
Version: 19.10.0.dev0
Summary: kernunos: automated wep app security reconnaissance.
Home-page: https://gitlab.com/agu3rra/kernunos
Author: Andre Guerra
Author-email: agu3rra@gmail.com
License: MIT
Keywords: web application reconnaissance automation
Platform: UNKNOWN
